lln_json_parser/__init__.py
lln_json_parser/parser.py
lln_json_parser/types.py
lln_json_parser/tests/__init__.py
lln_json_parser/tests/example.json
lln_json_parser/tests/test_parser.py
lln_json_parser-0.1.3.dist-info/LICENSE
lln_json_parser-0.1.3.dist-info/METADATA
lln_json_parser-0.1.3.dist-info/WHEEL
lln_json_parser-0.1.3.dist-info/top_level.txt
lln_json_parser-0.1.3.dist-info/RECORD
